risefor_lobbying/__init__.py
risefor_lobbying/admin.py
risefor_lobbying/apps.py
risefor_lobbying/djangoldp_urls.py
risefor_lobbying/models.py
risefor_lobbying/settings.py
risefor_lobbying/views.py
risefor_lobbying/elected-officials/fichier_deputes_commissions.csv
risefor_lobbying/elected-officials/fichier_deputes_commissions_20-09-2020.csv
risefor_lobbying/elected-officials/fichier_deputes_commissions_rip-animaux.csv
risefor_lobbying/elected-officials/fichier_senateurs_commissions.csv
risefor_lobbying/management/commands/import_elected.py
risefor_lobbying/migrations/0001_initial.py
risefor_lobbying/migrations/0002_auto_20200621_1128.py
risefor_lobbying/migrations/0003_auto_20200621_1751.py
risefor_lobbying/migrations/0004_auto_20200621_1753.py
risefor_lobbying/migrations/0005_auto_20200621_1758.py
risefor_lobbying/migrations/0006_auto_20200621_1803.py
risefor_lobbying/migrations/0007_auto_20200621_1807.py
risefor_lobbying/migrations/0008_auto_20200622_2150.py
risefor_lobbying/migrations/0009_auto_20200622_2156.py
risefor_lobbying/migrations/0010_auto_20200622_2202.py
risefor_lobbying/migrations/0011_auto_20200622_2352.py
risefor_lobbying/migrations/0012_auto_20200730_1402.py
risefor_lobbying/migrations/0013_auto_20200903_1301.py
risefor_lobbying/migrations/0014_auto_20200908_2120.py
risefor_lobbying/migrations/0015_representative_position_campagne.py
risefor_lobbying/migrations/0016_auto_20200920_2056.py
risefor_lobbying/migrations/0017_auto_20201004_1947.py
risefor_lobbying/migrations/0018_auto_20201108_1536.py
risefor_lobbying/migrations/0019_auto_20201108_1538.py
risefor_lobbying/migrations/0020_auto_20201127_1731.py
risefor_lobbying/migrations/0021_remove_actiongroup_postcode.py
risefor_lobbying/migrations/0022_auto_20201127_1741.py
risefor_lobbying/migrations/0023_actiongroup_postcode.py
risefor_lobbying/migrations/0024_actiongroup_image.py
risefor_lobbying/migrations/0025_auto_20201127_1749.py
risefor_lobbying/migrations/__init__.py
risefor_lobbying-1.1.2.dist-info/LICENSE
risefor_lobbying-1.1.2.dist-info/METADATA
risefor_lobbying-1.1.2.dist-info/WHEEL
risefor_lobbying-1.1.2.dist-info/top_level.txt
risefor_lobbying-1.1.2.dist-info/RECORD
