Metadata-Version: 2.1
Name: risefor-lobbying
Version: 1.1.2
Summary: risefor is a citizen mobilization and lobbying tool that aims at helping citizens communicate with their elected officials. Use these packages to deploy everything you need! More information at https://risefor.org/
Home-page: https://git.startinblox.com/djangoldp-packages/risefor-lobbying
Author: RiseFor
Author-email: calum@startinblox.com
License: copyleft CC NC SA
Platform: UNKNOWN
Classifier: Programming Language :: Python :: 3
Requires-Dist: djangoldp (~=1.0)
Requires-Dist: djangoldp-conversation (~=1.0)
Provides-Extra: dev
Requires-Dist: factory-boy (>=2.11.0) ; extra == 'dev'
